rows/__init__.py
rows/cli.py
rows/fields.py
rows/localization.py
rows/operations.py
rows/table.py
rows/utils.py
rows/plugins/__init__.py
rows/plugins/dicts.py
rows/plugins/ods.py
rows/plugins/plugin_csv.py
rows/plugins/plugin_html.py
rows/plugins/plugin_json.py
rows/plugins/plugin_parquet.py
rows/plugins/plugin_pdf.py
rows/plugins/postgresql.py
rows/plugins/sqlite.py
rows/plugins/txt.py
rows/plugins/utils.py
rows/plugins/xls.py
rows/plugins/xlsx.py
rows/plugins/xpath.py
rows-0.4.1.dist-info/AUTHORS.md
rows-0.4.1.dist-info/LICENSE
rows-0.4.1.dist-info/METADATA
rows-0.4.1.dist-info/WHEEL
rows-0.4.1.dist-info/dependency_links.txt
rows-0.4.1.dist-info/entry_points.txt
rows-0.4.1.dist-info/top_level.txt
rows-0.4.1.dist-info/RECORD
